tomlkit/__init__.py
tomlkit/_compat.py
tomlkit/_utils.py
tomlkit/api.py
tomlkit/container.py
tomlkit/exceptions.py
tomlkit/items.py
tomlkit/parser.py
tomlkit/py.typed
tomlkit/source.py
tomlkit/toml_char.py
tomlkit/toml_document.py
tomlkit/toml_file.py
tomlkit-0.9.1.dist-info/LICENSE
tomlkit-0.9.1.dist-info/WHEEL
tomlkit-0.9.1.dist-info/METADATA
tomlkit-0.9.1.dist-info/RECORD
