Metadata-Version: 2.1
Name: tomlkit
Version: 0.9.1
Summary: Style preserving TOML library
Home-page: https://github.com/sdispater/tomlkit
License: MIT
Author: Sébastien Eustace
Author-email: sebastien@eustace.io
Requires-Python: >=3.6,<4.0
Classifier: License :: OSI Approved :: MIT License
Classifier: Programming Language :: Python :: 3
Classifier: Programming Language :: Python :: 3.10
Classifier: Programming Language :: Python :: 3.6
Classifier: Programming Language :: Python :: 3.7
Classifier: Programming Language :: Python :: 3.8
Classifier: Programming Language :: Python :: 3.9
Project-URL: Repository, https://github.com/sdispater/tomlkit
